testcontainers_yt_local/__init__.py
testcontainers_yt_local/base.py
testcontainers_yt_local/container.py
testcontainers_yt_local/external.py
testcontainers_yt_local/fixtures.py
testcontainers_yt_local/py.typed
testcontainers_yt_local-0.17.0.dist-info/licenses/LICENSE
tests/conftest.py
tests/test_yt_local.py
testcontainers_yt_local-0.17.0.dist-info/METADATA
testcontainers_yt_local-0.17.0.dist-info/WHEEL
testcontainers_yt_local-0.17.0.dist-info/entry_points.txt
testcontainers_yt_local-0.17.0.dist-info/top_level.txt
testcontainers_yt_local-0.17.0.dist-info/RECORD
