Metadata-Version: 2.4
Name: testcontainers-yt-local
Version: 0.17.0
Summary: Testcontainer for Yt
Author: Dmitriy Fedorov
License: Apache 2.0
Project-URL: Homepage, https://github.com/dmi-feo/testcontainers-yt-local
Project-URL: Repository, https://github.com/dmi-feo/testcontainers-yt-local.git
Project-URL: Issues, https://github.com/dmi-feo/testcontainers-yt-local/issues
Project-URL: Changelog, https://github.com/dmi-feo/testcontainers-yt-local/blob/main/CHANGELOG.md
Keywords: testing,docker,test automation,yt,ytsaurus,pytest
Requires-Python: >=3.10
License-File: LICENSE
Requires-Dist: testcontainers~=4.10.0
Requires-Dist: ytsaurus-client<0.14
Requires-Dist: ytsaurus-yson<0.5
Requires-Dist: deepmerge<1.2
Provides-Extra: pytest
Requires-Dist: pytest<9; extra == "pytest"
Provides-Extra: tests
Requires-Dist: pytest<9; extra == "tests"
Requires-Dist: requests<3; extra == "tests"
Provides-Extra: release
Requires-Dist: bump-my-version==0.18.3; extra == "release"
Requires-Dist: generate-changelog==0.10.0; extra == "release"
Dynamic: license-file
